NanoImgPro/NanoImgPro.py
NanoImgPro/__init__.py
NanoImgPro-0.2.3.dist-info/LICENSE
NanoImgPro-0.2.3.dist-info/METADATA
NanoImgPro-0.2.3.dist-info/WHEEL
NanoImgPro-0.2.3.dist-info/top_level.txt
NanoImgPro-0.2.3.dist-info/RECORD
